traffic_light_controller_testbench.sv
    module traffic_light_controller (
        input logic clk,
        input logic reset,
        output logic red_light,
        output logic yellow_light,
        output logic green_light
    );

        typedef enum  { 
            RED_STATE,
            RED_YELLOW_STATE,
            YELLOW_STATE,
            GREEN_STATE
        } traffic_state_t;

        traffic_state_t current_state, next_state;
        logic [3:0] counter;

        parameter RED_TIME = 4'd10;
        parameter YELLOW_TIME = 4'd2;
        parameter GREEN_TIME = 4'd8;

        always_ff@(posedge clk) begin
            if (reset) begin
                current_state <= RED_STATE;
                counter <= 4'd0;
            end else begin
                current_state <= next_state;
                if (current_state != next_state) begin
                    counter <= 4'd0;
                end else begin
                    counter <= counter +1;
                end
                end
            end
        
        always_comb begin
            //next_state = current_state;
            red_light = 1'b0;
            yellow_light = 1'b0;
            green_light = 1'b0;

            case (current_state)
            RED_STATE :  begin
                red_light = 1'b1;
                    if (counter == RED_TIME-1) begin
                        next_state = RED_YELLOW_STATE;                        
                    end
            end
            RED_YELLOW_STATE : begin
                yellow_light = 1'b1;
                if (counter == YELLOW_TIME-1) begin
                    next_state = GREEN_STATE;
                                        
                end
            end
            GREEN_STATE : begin
                green_light = 1'b1;
                if (counter == GREEN_TIME-1) begin
                    next_state = YELLOW_STATE;
                                        
                end
            end
            YELLOW_STATE : begin
                yellow_light =1;
                if (counter == YELLOW_TIME-1) begin
                    next_state = RED_STATE;
                                        
                end
            end
                default: begin
                    next_state = RED_STATE;
                end
            endcase
        end

    endmodule

traffic_light_controller.sv

`timescale 1ns/1ps
`include "test.sv"


module tb;

    logic clk;
    logic reset;
    logic red_light;
    logic yellow_light;
    logic green_light;

    traffic_light_controller DUT (
        .clk(clk),
        .reset(reset),
        .red_light(red_light),
        .yellow_light(yellow_light),
        .green_light(green_light));

    
    parameter CLK_PERIOD = 10;

    initial begin
        clk = 0;
        forever #(CLK_PERIOD /2 ) clk = ~clk;
    end

    initial begin
        $dumpfile("dump.vcd");
        $dumpvars(1);
        $monitor("Time=%0d | CLK=%b | Reset=%b | Current State (from DUT outputs): Red=%b, Yellow=%b, Green=%b, ||Counter: %d ||",
                 $time, clk, reset, red_light, yellow_light, green_light,DUT.counter);
        reset =1; 
      #(CLK_PERIOD *1);
        $display("=========================================RESET DONE=========================================");
        reset = 0;
        
        #(CLK_PERIOD * 22 *2);
        reset = 1; #(CLK_PERIOD *2);
        $display("=========================================RESET AGAIN=========================================");
        reset = 0;
        #(CLK_PERIOD * 22 *4);
        $display("=========================================TEST COMPLETE=========================================");
        $finish;
    end

endmodule

dump.vcd
$date
	Thu Jul 17 00:55:00 2025
$end
$version
	Icarus Verilog
$end
$timescale
	1ps
$end
$scope module tb $end
$var wire 1 ! yellow_light $end
$var wire 1 " red_light $end
$var wire 1 # green_light $end
$var parameter 32 $ CLK_PERIOD $end
$var reg 1 % clk $end
$var reg 1 & reset $end
$upscope $end
$enddefinitions $end
$comment Show the parameter values. $end
$dumpall
b1010 $
$end
#0
$dumpvars
1&
0%
0#
1"
0!
$end
#5000
1"
1%
#10000
0%
0&
#15000
1"
1%
#20000
0%
#25000
1"
1%
#30000
0%
#35000
1"
1%
#40000
0%
#45000
1"
1%
#50000
0%
#55000
1"
1%
#60000
0%
#65000
1"
1%
#70000
0%
#75000
1"
1%
#80000
0%
#85000
1"
1%
#90000
0%
#95000
1"
1%
#100000
0%
#105000
1!
0"
1%
#110000
0%
#115000
1!
1%
#120000
0%
#125000
1#
0!
1%
#130000
0%
#135000
1#
1%
#140000
0%
#145000
1#
1%
#150000
0%
#155000
1#
1%
#160000
0%
#165000
1#
1%
#170000
0%
#175000
1#
1%
#180000
0%
#185000
1#
1%
#190000
0%
#195000
1#
1%
#200000
0%
#205000
1!
0#
1%
#210000
0%
#215000
1!
1%
#220000
0%
#225000
1"
0!
1%
#230000
0%
#235000
1"
1%
#240000
0%
#245000
1"
1%
#250000
0%
#255000
1"
1%
#260000
0%
#265000
1"
1%
#270000
0%
#275000
1"
1%
#280000
0%
#285000
1"
1%
#290000
0%
#295000
1"
1%
#300000
0%
#305000
1"
1%
#310000
0%
#315000
1"
1%
#320000
0%
#325000
1!
0"
1%
#330000
0%
#335000
1!
1%
#340000
0%
#345000
1#
0!
1%
#350000
0%
#355000
1#
1%
#360000
0%
#365000
1#
1%
#370000
0%
#375000
1#
1%
#380000
0%
#385000
1#
1%
#390000
0%
#395000
1#
1%
#400000
0%
#405000
1#
1%
#410000
0%
#415000
1#
1%
#420000
0%
#425000
1!
0#
1%
#430000
0%
#435000
1!
1%
#440000
0%
#445000
1"
0!
1%
#450000
0%
1&
#455000
1%
#460000
0%
#465000
1%
#470000
0%
0&
#475000
1"
1%
#480000
0%
#485000
1"
1%
#490000
0%
#495000
1"
1%
#500000
0%
#505000
1"
1%
#510000
0%
#515000
1"
1%
#520000
0%
#525000
1"
1%
#530000
0%
#535000
1"
1%
#540000
0%
#545000
1"
1%
#550000
0%
#555000
1"
1%
#560000
0%
#565000
1!
0"
1%
#570000
0%
#575000
1!
1%
#580000
0%
#585000
1#
0!
1%
#590000
0%
#595000
1#
1%
#600000
0%
#605000
1#
1%
#610000
0%
#615000
1#
1%
#620000
0%
#625000
1#
1%
#630000
0%
#635000
1#
1%
#640000
0%
#645000
1#
1%
#650000
0%
#655000
1#
1%
#660000
0%
#665000
1!
0#
1%
#670000
0%
#675000
1!
1%
#680000
0%
#685000
1"
0!
1%
#690000
0%
#695000
1"
1%
#700000
0%
#705000
1"
1%
#710000
0%
#715000
1"
1%
#720000
0%
#725000
1"
1%
#730000
0%
#735000
1"
1%
#740000
0%
#745000
1"
1%
#750000
0%
#755000
1"
1%
#760000
0%
#765000
1"
1%
#770000
0%
#775000
1"
1%
#780000
0%
#785000
1!
0"
1%
#790000
0%
#795000
1!
1%
#800000
0%
#805000
1#
0!
1%
#810000
0%
#815000
1#
1%
#820000
0%
#825000
1#
1%
#830000
0%
#835000
1#
1%
#840000
0%
#845000
1#
1%
#850000
0%
#855000
1#
1%
#860000
0%
#865000
1#
1%
#870000
0%
#875000
1#
1%
#880000
0%
#885000
1!
0#
1%
#890000
0%
#895000
1!
1%
#900000
0%
#905000
1"
0!
1%
#910000
0%
#915000
1"
1%
#920000
0%
#925000
1"
1%
#930000
0%
#935000
1"
1%
#940000
0%
#945000
1"
1%
#950000
0%
#955000
1"
1%
#960000
0%
#965000
1"
1%
#970000
0%
#975000
1"
1%
#980000
0%
#985000
1"
1%
#990000
0%
#995000
1"
1%
#1000000
0%
#1005000
1!
0"
1%
#1010000
0%
#1015000
1!
1%
#1020000
0%
#1025000
1#
0!
1%
#1030000
0%
#1035000
1#
1%
#1040000
0%
#1045000
1#
1%
#1050000
0%
#1055000
1#
1%
#1060000
0%
#1065000
1#
1%
#1070000
0%
#1075000
1#
1%
#1080000
0%
#1085000
1#
1%
#1090000
0%
#1095000
1#
1%
#1100000
0%
#1105000
1!
0#
1%
#1110000
0%
#1115000
1!
1%
#1120000
0%
#1125000
1"
0!
1%
#1130000
0%
#1135000
1"
1%
#1140000
0%
#1145000
1"
1%
#1150000
0%
#1155000
1"
1%
#1160000
0%
#1165000
1"
1%
#1170000
0%
#1175000
1"
1%
#1180000
0%
#1185000
1"
1%
#1190000
0%
#1195000
1"
1%
#1200000
0%
#1205000
1"
1%
#1210000
0%
#1215000
1"
1%
#1220000
0%
#1225000
1!
0"
1%
#1230000
0%
#1235000
1!
1%
#1240000
0%
#1245000
1#
0!
1%
#1250000
0%
#1255000
1#
1%
#1260000
0%
#1265000
1#
1%
#1270000
0%
#1275000
1#
1%
#1280000
0%
#1285000
1#
1%
#1290000
0%
#1295000
1#
1%
#1300000
0%
#1305000
1#
1%
#1310000
0%
#1315000
1#
1%
#1320000
0%
#1325000
1!
0#
1%
#1330000
0%
#1335000
1!
1%
#1340000
0%
#1345000
1"
0!
1%
